{
    "name": "faery_open",
    "speed": 1,
    "mode": "normal",
    "data": {
        "body/arm_r": {
            "angle": [
                {
                    "frame": 0,
                    "value": 0
                },
                {
                    "frame": 517,
                    "value": 42
                },
                {
                    "frame": 733,
                    "value": -5
                },
                {
                    "frame": 933,
                    "value": 0
                }
            ]
        },
        "body/arm_l": {
            "angle": [
                {
                    "frame": 0,
                    "value": 0
                },
                {
                    "frame": 517,
                    "value": 58
                },
                {
                    "frame": 733,
                    "value": -21
                },
                {
                    "frame": 933,
                    "value": 0
                }
            ]
        },
        "leg1_l": {
            "angle": [
                {
                    "frame": 0,
                    "value": -16
                },
                {
                    "frame": 517,
                    "value": 11
                },
                {
                    "frame": 733,
                    "value": 7
                },
                {
                    "frame": 933,
                    "value": -16
                }
            ]
        },
        "leg1_r": {
            "angle": [
                {
                    "frame": 0,
                    "value": 0
                },
                {
                    "frame": 517,
                    "value": 15
                },
                {
                    "frame": 733,
                    "value": 17
                },
                {
                    "frame": 933,
                    "value": 0
                }
            ]
        },
        "leg1_r/leg2_r": {
            "angle": [
                {
                    "frame": 0,
                    "value": 0
                },
                {
                    "frame": 517,
                    "value": -54
                },
                {
                    "frame": 733,
                    "value": 15
                },
                {
                    "frame": 933,
                    "value": 0
                }
            ]
        },
        "leg1_l/leg2_l": {
            "angle": [
                {
                    "frame": 0,
                    "value": 80
                },
                {
                    "frame": 517,
                    "value": -13
                },
                {
                    "frame": 733,
                    "value": 60
                },
                {
                    "frame": 933,
                    "value": 80
                }
            ]
        },
        "body/head": {
            "angle": [
                {
                    "frame": 0,
                    "value": 0
                },
                {
                    "frame": 517,
                    "value": 11
                },
                {
                    "frame": 733,
                    "value": 1
                },
                {
                    "frame": 933,
                    "value": 0
                }
            ]
        },
        "wing_l": {
            "scaleX": [
                {
                    "frame": 0,
                    "value": 1
                },
                {
                    "frame": 167,
                    "value": 0.5
                },
                {
                    "frame": 333,
                    "value": 1
                },
                {
                    "frame": 500,
                    "value": 0.5
                },
                {
                    "frame": 650,
                    "value": 1
                },
                {
                    "frame": 800,
                    "value": 0.5
                },
                {
                    "frame": 933,
                    "value": 1
                }
            ]
        },
        "wing_r": {
            "scaleX": [
                {
                    "frame": 0,
                    "value": 1
                },
                {
                    "frame": 167,
                    "value": 0.5
                },
                {
                    "frame": 333,
                    "value": 1
                },
                {
                    "frame": 500,
                    "value": 0.5
                },
                {
                    "frame": 650,
                    "value": 1
                },
                {
                    "frame": 800,
                    "value": 0.5
                },
                {
                    "frame": 933,
                    "value": 1
                }
            ]
        },
        "fx_wing": {
            "frameName": [
                {
                    "frame": 0,
                    "value": "wing1.png"
                },
                {
                    "frame": 133,
                    "value": "wing2.png"
                },
                {
                    "frame": 250,
                    "value": "wing3.png"
                },
                {
                    "frame": 383,
                    "value": "wing4.png"
                },
                {
                    "frame": 517,
                    "value": "wing5.png"
                },
                {
                    "frame": 650,
                    "value": "wing6.png"
                },
                {
                    "frame": 817,
                    "value": "wing7.png"
                },
                {
                    "frame": 933,
                    "value": "wing1.png"
                }
            ]
        },
        "body/arm_l/star/fx_star": {
            "frameName": [
                {
                    "frame": 0,
                    "value": "star_anim1.png"
                },
                {
                    "frame": 183,
                    "value": "star_anim2.png"
                },
                {
                    "frame": 400,
                    "value": "star_anim3.png"
                },
                {
                    "frame": 617,
                    "value": "star_anim4.png"
                },
                {
                    "frame": 800,
                    "value": "star_anim5.png"
                },
                {
                    "frame": 933,
                    "value": "star_anim1.png"
                }
            ]
        },
        "body/arm_l/star": {
            "angle": [
                {
                    "frame": 0,
                    "value": 6
                },
                {
                    "frame": 267,
                    "value": 17
                },
                {
                    "frame": 517,
                    "value": -14
                },
                {
                    "frame": 733,
                    "value": 5
                },
                {
                    "frame": 933,
                    "value": 6
                }
            ]
        }
    }
}